scripting/__init__.py
scripting/conda.py
scripting/contexts.py
scripting/git.py
scripting/prompting.py
scripting/termcolors.py
scripting/unix.py
scripting/url.py
scripting/tests/__init__.py
scripting/tests/test_cp.py
scripting/tests/test_prompting.py
py_scripting-0.2.6.dist-info/LICENSE
py_scripting-0.2.6.dist-info/METADATA
py_scripting-0.2.6.dist-info/WHEEL
py_scripting-0.2.6.dist-info/top_level.txt
py_scripting-0.2.6.dist-info/RECORD
